acmetric_plotting/Oswald-Regular.ttf
acmetric_plotting/__init__.py
acmetric_plotting/colors.py
acmetric_plotting/fonts.py
acmetric_plotting/params.py
acmetric_plotting/plots.py
acmetric_plotting-1.3.2.dist-info/LICENCE
acmetric_plotting-1.3.2.dist-info/METADATA
acmetric_plotting-1.3.2.dist-info/WHEEL
acmetric_plotting-1.3.2.dist-info/top_level.txt
acmetric_plotting-1.3.2.dist-info/RECORD
