Metadata-Version: 2.1
Name: acmetric_plotting
Version: 1.3.2
Summary: A package to easily build ACMetric branded plots
Author-email: Ivan <ivan@acmetric.com>, Jakob <jakob@acmetric.com>
Project-URL: Homepage, https://github.com/ACMetric/acmetric_package
Project-URL: Bug Tracker, https://github.com/ACMetric/acmetric_package/issues
Classifier: Programming Language :: Python :: 3
Classifier: Operating System :: OS Independent
Requires-Python: >=3.7
License-File: LICENCE
Requires-Dist: cycler >=0.11.0
Requires-Dist: matplotlib >=3.5
Requires-Dist: seaborn >=0.11.2
Requires-Dist: numpy >=1.20.0
Requires-Dist: scipy >=1.7.0
